{
  "Período": "12 de setembro de 1824 a 25 de maio de 1825",
  "Co-regentes": "Marquês de Caravelas Campos Vergueiro",
  "Antecessor(a)": "Francisco Pais Barreto",
  "Sucessor(a)": "José Carlos Mayrink da Silva Ferrão",
  "Nascimento": "05 de julho de 1785 Rio de Janeiro , Estado do Brasil",
  "Morte": "02 de dezembro de 1853 (68 anos) Rio de Janeiro , Império do Brasil",
  "Nacionalidade": "Brasileiro",
  "Progenitores": "Mãe: Joana Maria da Fonseca Costa Pai: José Joaquim de Lima e Silva",
  "Esposa": "Mariana Cândida de Oliveira Belo ( c. 1801)",
  "Filhos(as)": "Luís Alves • José Joaquim • Carlota Guilhermina",
  "Religião": "catolicismo romano",
  "Profissão": "militar e político",
  "Assinatura": "",
  "Barão da Barra Grande": "jul. 1841",
  "Lealdade": "Império do Brasil",
  "Serviço/ramo": "Exército Imperial",
  "Patente": "Brigadeiro",
  "Conflitos": "Confederação do Equador",
  "Condecorações": "Imperial Ordem do Cruzeiro"
}