{
  "Período": "1° de fevereiro de 1999 até 1° de janeiro de 2003",
  "Presidente": "Luiz Inácio Lula da Silva",
  "Antecessor(a)": "Júnia Marise",
  "Sucessor(a)": "Aelton Freitas",
  "Nome completo": "José Alencar Gomes da Silva",
  "Nascimento": "17 de outubro de 1931 Muriaé , MG",
  "Morte": "29 de março de 2011 (79 anos) São Paulo , SP",
  "Nacionalidade": "brasileiro",
  "Prêmio(s)": [
    "Ordem do Mérito Militar[1]",
    "Ordem do Infante D. Henrique[2]"
  ],
  "Esposa": "Mariza Gomes (c.1957-m.2011)",
  "Filhos(as)": "Maria da Graça, Patrícia e Josué Gomes",
  "Partido": [
    "PMDB(1993-2002)",
    "PL(2002-2005)",
    "PRB(2005-2011)"
  ],
  "Profissão": "empresário , político",
  "Assinatura": ""
}