{
  "Apelido(s)": "Cidade do Profeta",
  "Coordenadas": "24° 28′ 00″ N, 39° 36′ 00″ L",
  "País": "Arábia Saudita",
  "Província": "Medina",
  "Prefeito": "Abdulaziz Bin Majid (عبدالعزيز بن ماجد)",
  "Área total [ 1 ]": "589 km²",
  "• Área urbana": "293 km²",
  "População total ( Censo 2010) [ 2 ] [ 3 ]": "1 100 093 hab.",
  "• População urbana": "918 889",
  "Densidade": "1 687,9 hab./km²",
  "• Densidade urbana": "3 136,1 hab./km²",
  "Altitude [ 4 ]": "619 m",
  "Fuso horário": "Arabia Standard Time ( UTC+3 )"
}