{
  "Nome completo": "Polícia Civil do Estado de Santa Catarina",
  "Sigla": "PCSC",
  "Fundação": "1812 (213 anos)",
  "Tipo": "Força policial civil - polícia judiciária",
  "Subordinação": "Secretaria de Estado da Segurança Pública",
  "Direção superior": "Delegacia Geral da Polícia Civil",
  "Chefe": "Delegado Geral Marcos Flávio Ghizoni Júnior",
  "Legislação": "Constituição Federal , art. 144, IV e §§ 4º e 6º",
  "Sede": "Florianópolis , Santa Catarina Brasil",
  "Força de suporte": "SAer",
  "Empregados": "c. 3 700 policiais e peritos técnicos (2022) [ 1 ]"
}