{
  "Nascimento": "Eugène Adrien Roland Chacon Georges Garros 6 de outubro de 1888 São Dinis",
  "Morte": "5 de outubro de 1918 ( 29 anos ) Vouziers",
  "Sepultamento": "Vouziers",
  "Cidadania": "França",
  "Alma mater": [
    "Escola de Altos Estudos Comerciais de Paris",
    "Collège Stanislas",
    "Lycée Janson-de-Sailly"
  ],
  "Ocupação": "piloto , jogador de râguebi de quinze, militar",
  "Distinções": [
    "Oficial da Legião de Honra",
    "Mort pour la France",
    "Grande médaille de l'Aéro-Club de France"
  ],
  "Causa da morte": "morto em combate"
}