{
  "Gentílico": "valparaisense",
  "Coordenadas": "16° 03′ 57″ S, 47° 58′ 44″ O",
  "País": "Brasil",
  "Unidade federativa": "Goiás",
  "Região metropolitana": "Distrito Federal e Entorno",
  "Municípios limítrofes": "Novo Gama , Santa Maria (DF) , Cidade Ocidental e Luziânia",
  "Distância até a capital": "188 km",
  "Fundação": "15 de junho de 1995 (29 anos)",
  "Prefeito(a)": "Marcus Vinicius [ 1 ] ( MDB , 2025–2028)",
  "Área total [ 2 ]": "61,488 km²",
  "População total (Estimativa IBGE /2024 [ 3 ] )": "213 506 hab.",
  "• Posição": "GO: 7º",
  "Densidade": "3 472,3 hab./km²",
  "Clima": "tropical",
  "Altitude": "1080 m",
  "Fuso horário": "Hora de Brasília ( UTC−3 )",
  "IDH ( PNUD /2010 [ 4 ] )": "0,746 — alto",
  "PIB ( IBGE /2021 [ 5 ] )": "R$ 2 964 512,369 mil",
  "PIB per capita ( IBGE /2021 [ 5 ] )": "R$ 16 870,66",
  "Sítio": "valparaisodegoias.go.gov.br ( Prefeitura ) camaravalparaiso.go.gov.br ( Câmara )"
}